README.md
setup.cfg
setup.py
zk225_probability/Binomialdistribution.py
zk225_probability/Gaussiandistribution.py
zk225_probability/Generaldistribution.py
zk225_probability/__init__.py
zk225_probability.egg-info/PKG-INFO
zk225_probability.egg-info/SOURCES.txt
zk225_probability.egg-info/dependency_links.txt
zk225_probability.egg-info/not-zip-safe
zk225_probability.egg-info/top_level.txt